AUTHORS.rst
ChangeLog.rst
LICENSE
MANIFEST.in
README.md
requirements.txt
setup.cfg
setup.py
src/buildout_component/__init__.py
src/buildout_component/cli.py
src/buildout_component/contexts.py
src/buildout_component/errors.py
src/buildout_component/models.py
src/buildout_component/utils.py
src/buildout_component.egg-info/PKG-INFO
src/buildout_component.egg-info/SOURCES.txt
src/buildout_component.egg-info/dependency_links.txt
src/buildout_component.egg-info/entry_points.txt
src/buildout_component.egg-info/not-zip-safe
src/buildout_component.egg-info/requires.txt
src/buildout_component.egg-info/top_level.txt
src/buildout_component/__pycache__/__init__.cpython-38.pyc
src/buildout_component/__pycache__/cli.cpython-38.pyc
src/buildout_component/__pycache__/contexts.cpython-38.pyc
src/buildout_component/__pycache__/errors.cpython-38.pyc
src/buildout_component/__pycache__/models.cpython-38.pyc
src/buildout_component/__pycache__/utils.cpython-38.pyc