Metadata-Version: 1.1
Name: buildout-component
Version: 0.1.0
Summary: UNKNOWN
Home-page: https://www.nicestudio.com.tw/projects/Buildout Component/
Author: niceStuio, Inc.
Author-email: service@nicestudio.com.tw
License: GPL-3.0 License
Keywords: buildout_component
Platform: UNKNOWN
Classifier: Development Status :: 2 - Pre-Alpha
Classifier: Intended Audience :: Developers
Classifier: License :: OSI Approved :: BSD License
Classifier: Natural Language :: English
Classifier: Programming Language :: Python :: 2
Classifier: Programming Language :: Python :: 2.6
Classifier: Programming Language :: Python :: 2.7
Classifier: Programming Language :: Python :: 3
Classifier: Programming Language :: Python :: 3.3
Classifier: Programming Language :: Python :: 3.4
